chronus/SystemIntegration/__init__.py
chronus/SystemIntegration/application_runners/__init__.py
chronus/SystemIntegration/application_runners/hpcg.py
chronus/SystemIntegration/cpu_info_services/__init__.py
chronus/SystemIntegration/cpu_info_services/cpu_info_service.py
chronus/SystemIntegration/optimizers/__init__.py
chronus/SystemIntegration/optimizers/bruteforce_optmizer.py
chronus/SystemIntegration/optimizers/linear_regression.py
chronus/SystemIntegration/optimizers/random_tree_forrest.py
chronus/SystemIntegration/repositories/__init__.py
chronus/SystemIntegration/repositories/csv_repository.py
chronus/SystemIntegration/repositories/sqlite_repository.py
chronus/SystemIntegration/settings_interface/__init__.py
chronus/SystemIntegration/settings_interface/etc_storage.py
chronus/SystemIntegration/system_service_interfaces/__init__.py
chronus/SystemIntegration/system_service_interfaces/ipmi_system_service.py
chronus/__init__.py
chronus/__main__.py
chronus/application/__init__.py
chronus/application/benchmark_service.py
chronus/application/init_model_service.py
chronus/application/load_model_service.py
chronus/application/run_model_service.py
chronus/cli/__init__.py
chronus/cli/setup.py
chronus/domain/LocalSettings.py
chronus/domain/Run.py
chronus/domain/__init__.py
chronus/domain/benchmark.py
chronus/domain/configuration.py
chronus/domain/cpu_info.py
chronus/domain/interfaces/__init__.py
chronus/domain/interfaces/application_runner_interface.py
chronus/domain/interfaces/cpu_info_service_interface.py
chronus/domain/interfaces/optimizer_interface.py
chronus/domain/interfaces/repository_interface.py
chronus/domain/interfaces/settings_interface.py
chronus/domain/interfaces/system_service_interface.py
chronus/domain/model.py
chronus/domain/system_sample.py
chronus-0.3.13.dist-info/LICENSE
chronus-0.3.13.dist-info/METADATA
chronus-0.3.13.dist-info/WHEEL
chronus-0.3.13.dist-info/entry_points.txt
chronus-0.3.13.dist-info/RECORD
