Metadata-Version: 2.1
Name: chronus
Version: 0.3.13
Summary: A energy scheduling model, build for HPC.
Home-page: https://github.com/AndersSpringborg/chronus
License: MIT
Author: chronus
Author-email: aaspringborg@gmail.com
Requires-Python: >=3.9,<4.0
Classifier: Development Status :: 3 - Alpha
Classifier: Intended Audience :: Developers
Classifier: License :: OSI Approved :: MIT License
Classifier: Operating System :: OS Independent
Classifier: Programming Language :: Python :: 3
Classifier: Programming Language :: Python :: 3.9
Classifier: Programming Language :: Python :: 3.10
Classifier: Programming Language :: Python :: 3.11
Classifier: Programming Language :: Python :: 3
Classifier: Programming Language :: Python :: 3.9
Classifier: Topic :: Software Development :: Libraries :: Python Modules
Provides-Extra: model
Requires-Dist: dataclasses-json (>=0.5.7,<0.6.0)
Requires-Dist: matplotlib (>=3.7.1,<4.0.0)
Requires-Dist: pandas[model] (>=2.0.1,<3.0.0) ; extra == "model"
Requires-Dist: psutil (>=5.9.5,<6.0.0)
Requires-Dist: pyghmi (>=1.5.61,<2.0.0)
Requires-Dist: rich (>=12.6.0,<13.0.0)
Requires-Dist: scikit-learn (>=1.2.1,<2.0.0)
Requires-Dist: typer[all] (>=0.7.0,<0.8.0)
Project-URL: Repository, https://github.com/AndersSpringborg/chronus
